LICENSE.txt
README.md
setup.cfg
setup.py
Sehajbir_Singh_Mann_102003478.egg-info/PKG-INFO
Sehajbir_Singh_Mann_102003478.egg-info/SOURCES.txt
Sehajbir_Singh_Mann_102003478.egg-info/dependency_links.txt
Sehajbir_Singh_Mann_102003478.egg-info/entry_points.txt
Sehajbir_Singh_Mann_102003478.egg-info/requires.txt
Sehajbir_Singh_Mann_102003478.egg-info/top_level.txt
Topsis/102003478.py