Metadata-Version: 2.1
Name: Sehajbir-Singh-Mann-102003478
Version: 1.1.2
Summary: Topsis Package
Author: Sehajbir Singh Mann
Author-email: <smann1_be20@thapar.edu>
License: MIT License
Keywords: python,topsis,mcdm
Classifier: Development Status :: 1 - Planning
Classifier: Intended Audience :: Developers
Classifier: Programming Language :: Python :: 3
Classifier: Operating System :: Unix
Classifier: Operating System :: MacOS :: MacOS X
Classifier: Operating System :: Microsoft :: Windows
License-File: LICENSE.txt
